{
  "page_role": "detail",
  "items": [
    {
      "請求伝票番号": "2501135203",
      "得意先名": "ラルズホンブ　イツパン",
      "得意先コード": "(1135203)",
      "計上日": "01/31",
      "期間開始": "01/01",
      "期間終了": "01/14",
      "商品名": "ノグリラーメンマイルド　　　１２０ｇ",
      "ケース入数": "30",
      "数量": "4",
      "数量単位": "CS",
      "条件": "870",
      "条件区分": "CS",
      "条件備考": null,
      "金額": "3,480",
      "消費税率": "8.00%",
      "備考": "平田　和祝",
      "タイプ": null,
      "pdf_filename": "三菱食品東日本_2025.01 (2)-9-12.pdf",
      "page_number": 2,
      "item_order": 1,
      "item_id": 68,
      "version": 1,
      "review_status": {
        "first_review": {
          "checked": false,
          "reviewed_at": null
        },
        "second_review": {
          "checked": false,
          "reviewed_at": null
        }
      }
    },
    {
      "請求伝票番号": "5156688",
      "得意先名": "ラルズホンブ　イツパン",
      "得意先コード": "(1135203)",
      "計上日": "01/31",
      "期間開始": "01/01",
      "期間終了": "01/20",
      "商品名": "辛ラーメン　ミニカップ　　　４９ｇ",
      "ケース入数": "24",
      "数量": "6",
      "数量単位": "CS",
      "条件": "408",
      "条件区分": "CS",
      "条件備考": null,
      "金額": "102",
      "消費税率": "8.00%",
      "備考": null,
      "タイプ": null,
      "pdf_filename": "三菱食品東日本_2025.01 (2)-9-12.pdf",
      "page_number": 2,
      "item_order": 2,
      "item_id": 69,
      "version": 1,
      "review_status": {
        "first_review": {
          "checked": false,
          "reviewed_at": null
        },
        "second_review": {
          "checked": false,
          "reviewed_at": null
        }
      }
    },
    {
      "請求伝票番号": "5391635",
      "得意先名": "ラルズホンブ　イツパン",
      "得意先コード": "(1135203)",
      "計上日": "01/31",
      "期間開始": "01/01",
      "期間終了": "01/21",
      "商品名": "辛ラーメンキムチ袋　３Ｐ　　１２０ｇ×３",
      "ケース入数": "12",
      "数量": "7",
      "数量単位": "CS",
      "条件": "1,668",
      "条件区分": "CS",
      "条件備考": null,
      "金額": "11,676",
      "消費税率": "8.00%",
      "備考": null,
      "タイプ": null,
      "pdf_filename": "三菱食品東日本_2025.01 (2)-9-12.pdf",
      "page_number": 2,
      "item_order": 3,
      "item_id": 70,
      "version": 1,
      "review_status": {
        "first_review": {
          "checked": false,
          "reviewed_at": null
        },
        "second_review": {
          "checked": false,
          "reviewed_at": null
        }
      }
    },
    {
      "請求伝票番号": "6339259",
      "得意先名": "ラルズホンブ　イツパン",
      "得意先コード": "(1135203)",
      "計上日": "01/31",
      "期間開始": "01/01",
      "期間終了": "01/25",
      "商品名": "辛ラーメンキムチ　袋　　　　１２０ｇ",
      "ケース入数": "30",
      "数量": "5",
      "数量単位": "CS",
      "条件": "1,080",
      "条件区分": "CS",
      "条件備考": null,
      "金額": "5,400",
      "消費税率": "8.00%",
      "備考": null,
      "タイプ": null,
      "pdf_filename": "三菱食品東日本_2025.01 (2)-9-12.pdf",
      "page_number": 2,
      "item_order": 4,
      "item_id": 71,
      "version": 1,
      "review_status": {
        "first_review": {
          "checked": false,
          "reviewed_at": null
        },
        "second_review": {
          "checked": false,
          "reviewed_at": null
        }
      }
    },
    {
      "請求伝票番号": "6540524",
      "得意先名": "ラルズホンブ　イツパン",
      "得意先コード": "(1135203)",
      "計上日": "01/31",
      "期間開始": "01/01",
      "期間終了": "01/26",
      "商品名": "辛ラーメンバケツカップ　　　１１４ｇ",
      "ケース入数": "12",
      "数量": "8",
      "数量単位": "CS",
      "条件": "396",
      "条件区分": "CS",
      "条件備考": null,
      "金額": "3,168",
      "消費税率": "8.00%",
      "備考": null,
      "タイプ": null,
      "pdf_filename": "三菱食品東日本_2025.01 (2)-9-12.pdf",
      "page_number": 2,
      "item_order": 5,
      "item_id": 72,
      "version": 1,
      "review_status": {
        "first_review": {
          "checked": false,
          "reviewed_at": null
        },
        "second_review": {
          "checked": false,
          "reviewed_at": null
        }
      }
    },
    {
      "請求伝票番号": "6540534",
      "得意先名": "ラルズホンブ　イツパン",
      "得意先コード": "(1135203)",
      "計上日": "01/31",
      "期間開始": "01/01",
      "期間終了": "01/26",
      "商品名": "辛ラーメンキムチカップ　　　６８ｇ",
      "ケース入数": "12",
      "数量": "20",
      "数量単位": "CS",
      "条件": "600",
      "条件区分": "CS",
      "条件備考": null,
      "金額": "12,000",
      "消費税率": "8.00%",
      "備考": null,
      "タイプ": null,
      "pdf_filename": "三菱食品東日本_2025.01 (2)-9-12.pdf",
      "page_number": 2,
      "item_order": 6,
      "item_id": 73,
      "version": 1,
      "review_status": {
        "first_review": {
          "checked": false,
          "reviewed_at": null
        },
        "second_review": {
          "checked": false,
          "reviewed_at": null
        }
      }
    },
    {
      "請求伝票番号": "6719166",
      "得意先名": "ラルズホンブ　イツパン",
      "得意先コード": "(1135203)",
      "計上日": "01/31",
      "期間開始": "01/01",
      "期間終了": "01/27",
      "商品名": "本場韓国コムタンラーメン　袋１１１ｇ",
      "ケース入数": "20",
      "数量": "9",
      "数量単位": "CS",
      "条件": "840",
      "条件区分": "CS",
      "条件備考": null,
      "金額": "7,560",
      "消費税率": "8.00%",
      "備考": null,
      "タイプ": null,
      "pdf_filename": "三菱食品東日本_2025.01 (2)-9-12.pdf",
      "page_number": 2,
      "item_order": 7,
      "item_id": 74,
      "version": 1,
      "review_status": {
        "first_review": {
          "checked": false,
          "reviewed_at": null
        },
        "second_review": {
          "checked": false,
          "reviewed_at": null
        }
      }
    },
    {
      "請求伝票番号": "6719168",
      "得意先名": "ラルズホンブ　イツパン",
      "得意先コード": "(1135203)",
      "計上日": "01/31",
      "期間開始": "01/01",
      "期間終了": "01/27",
      "商品名": "チャパグリカップ　　　　　　１１４ｇ",
      "ケース入数": "12",
      "数量": "13",
      "数量単位": "CS",
      "条件": "486",
      "条件区分": "CS",
      "条件備考": null,
      "金額": "6,318",
      "消費税率": "8.00%",
      "備考": null,
      "タイプ": null,
      "pdf_filename": "三菱食品東日本_2025.01 (2)-9-12.pdf",
      "page_number": 2,
      "item_order": 8,
      "item_id": 75,
      "version": 1,
      "review_status": {
        "first_review": {
          "checked": false,
          "reviewed_at": null
        },
        "second_review": {
          "checked": false,
          "reviewed_at": null
        }
      }
    },
    {
      "請求伝票番号": "6719169",
      "得意先名": "ラルズホンブ　イツパン",
      "得意先コード": "(1135203)",
      "計上日": "01/31",
      "期間開始": "01/01",
      "期間終了": "01/27",
      "商品名": "辛ラーメン焼きそばカップ　　１０３ｇ",
      "ケース入数": "12",
      "数量": "10",
      "数量単位": "CS",
      "条件": "486",
      "条件区分": "CS",
      "条件備考": null,
      "金額": "4,860",
      "消費税率": "8.00%",
      "備考": null,
      "タイプ": null,
      "pdf_filename": "三菱食品東日本_2025.01 (2)-9-12.pdf",
      "page_number": 2,
      "item_order": 9,
      "item_id": 76,
      "version": 1,
      "review_status": {
        "first_review": {
          "checked": false,
          "reviewed_at": null
        },
        "second_review": {
          "checked": false,
          "reviewed_at": null
        }
      }
    },
    {
      "請求伝票番号": "6952169",
      "得意先名": "ラルズホンブ　イツパン",
      "得意先コード": "(1135203)",
      "計上日": "01/31",
      "期間開始": "01/01",
      "期間終了": "01/28",
      "商品名": "辛ラーメン焼きそばカップ　　１０３ｇ",
      "ケース入数": "12",
      "数量": "6",
      "数量単位": "CS",
      "条件": "486",
      "条件区分": "CS",
      "条件備考": null,
      "金額": "2,916",
      "消費税率": "8.00%",
      "備考": null,
      "タイプ": null,
      "pdf_filename": "三菱食品東日本_2025.01 (2)-9-12.pdf",
      "page_number": 2,
      "item_order": 10,
      "item_id": 77,
      "version": 1,
      "review_status": {
        "first_review": {
          "checked": false,
          "reviewed_at": null
        },
        "second_review": {
          "checked": false,
          "reviewed_at": null
        }
      }
    },
    {
      "請求伝票番号": "7201907",
      "得意先名": "ラルズホンブ　イツパン",
      "得意先コード": "(1135203)",
      "計上日": "01/31",
      "期間開始": "01/01",
      "期間終了": "01/29",
      "商品名": "チャパゲティ　　　　　　　　１４０ｇ",
      "ケース入数": "30",
      "数量": "4",
      "数量単位": "CS",
      "条件": "1,005",
      "条件区分": "CS",
      "条件備考": null,
      "金額": "4,020",
      "消費税率": "8.00%",
      "備考": null,
      "タイプ": null,
      "pdf_filename": "三菱食品東日本_2025.01 (2)-9-12.pdf",
      "page_number": 2,
      "item_order": 11,
      "item_id": 78,
      "version": 1,
      "review_status": {
        "first_review": {
          "checked": false,
          "reviewed_at": null
        },
        "second_review": {
          "checked": false,
          "reviewed_at": null
        }
      }
    },
    {
      "請求伝票番号": "7201908",
      "得意先名": "ラルズホンブ　イツパン",
      "得意先コード": "(1135203)",
      "計上日": "01/31",
      "期間開始": "01/01",
      "期間終了": "01/29",
      "商品名": "チャパゲティ　　　　　　　　１４０ｇ",
      "ケース入数": "30",
      "数量": "9",
      "数量単位": "CS",
      "条件": "1,005",
      "条件区分": "CS",
      "条件備考": null,
      "金額": "9,045",
      "消費税率": "8.00%",
      "備考": null,
      "タイプ": null,
      "pdf_filename": "三菱食品東日本_2025.01 (2)-9-12.pdf",
      "page_number": 2,
      "item_order": 12,
      "item_id": 79,
      "version": 1,
      "review_status": {
        "first_review": {
          "checked": false,
          "reviewed_at": null
        },
        "second_review": {
          "checked": false,
          "reviewed_at": null
        }
      }
    },
    {
      "請求伝票番号": "7201911",
      "得意先名": "ラルズホンブ　イツパン",
      "得意先コード": "(1135203)",
      "計上日": "01/31",
      "期間開始": "01/01",
      "期間終了": "01/29",
      "商品名": "辛ラーメンバケツカップ　　　１１４ｇ",
      "ケース入数": "12",
      "数量": "22",
      "数量単位": "CS",
      "条件": "396",
      "条件区分": "CS",
      "条件備考": null,
      "金額": "7,128",
      "消費税率": "8.00%",
      "備考": null,
      "タイプ": null,
      "pdf_filename": "三菱食品東日本_2025.01 (2)-9-12.pdf",
      "page_number": 2,
      "item_order": 13,
      "item_id": 80,
      "version": 1,
      "review_status": {
        "first_review": {
          "checked": false,
          "reviewed_at": null
        },
        "second_review": {
          "checked": false,
          "reviewed_at": null
        }
      }
    },
    {
      "請求伝票番号": "7201913",
      "得意先名": "ラルズホンブ　イツパン",
      "得意先コード": "(1135203)",
      "計上日": "01/31",
      "期間開始": "01/01",
      "期間終了": "01/29",
      "商品名": "辛ラーメンブラック　　　　　１３０ｇ",
      "ケース入数": "20",
      "数量": "11",
      "数量単位": "CS",
      "条件": "510",
      "条件区分": "CS",
      "条件備考": null,
      "金額": "5,610",
      "消費税率": "8.00%",
      "備考": null,
      "タイプ": null,
      "pdf_filename": "三菱食品東日本_2025.01 (2)-9-12.pdf",
      "page_number": 2,
      "item_order": 14,
      "item_id": 81,
      "version": 1,
      "review_status": {
        "first_review": {
          "checked": false,
          "reviewed_at": null
        },
        "second_review": {
          "checked": false,
          "reviewed_at": null
        }
      }
    },
    {
      "請求伝票番号": "7201916",
      "得意先名": "ラルズホンブ　イツパン",
      "得意先コード": "(1135203)",
      "計上日": "01/31",
      "期間開始": "01/01",
      "期間終了": "01/29",
      "商品名": "辛ラーメンカップ　　　　　　６８ｇ",
      "ケース入数": "12",
      "数量": "20",
      "数量単位": "CS",
      "条件": "600",
      "条件区分": "CS",
      "条件備考": null,
      "金額": "12,000",
      "消費税率": "8.00%",
      "備考": null,
      "タイプ": null,
      "pdf_filename": "三菱食品東日本_2025.01 (2)-9-12.pdf",
      "page_number": 2,
      "item_order": 15,
      "item_id": 82,
      "version": 1,
      "review_status": {
        "first_review": {
          "checked": false,
          "reviewed_at": null
        },
        "second_review": {
          "checked": false,
          "reviewed_at": null
        }
      }
    }
  ]
}